dodo_is_api/__init__.py
dodo_is_api/connection/__init__.py
dodo_is_api/connection/asynchronous.py
dodo_is_api/connection/base.py
dodo_is_api/connection/synchronous.py
dodo_is_api/exceptions.py
dodo_is_api/logger.py
dodo_is_api/models/__init__.py
dodo_is_api/models/channel_stop_types.py
dodo_is_api/models/country_codes.py
dodo_is_api/models/courier_orders.py
dodo_is_api/models/delivery_statistics.py
dodo_is_api/models/delivery_transport_names.py
dodo_is_api/models/late_delivery_vouchers.py
dodo_is_api/models/order_sources.py
dodo_is_api/models/orders_handover_statistics.py
dodo_is_api/models/orders_handover_time.py
dodo_is_api/models/production_productivity_statistics.py
dodo_is_api/models/sales_channels.py
dodo_is_api/models/stop_sales.py
dodo_is_api-0.8.0.dist-info/LICENSE
dodo_is_api-0.8.0.dist-info/WHEEL
dodo_is_api-0.8.0.dist-info/METADATA
dodo_is_api-0.8.0.dist-info/RECORD
