Metadata-Version: 2.1
Name: dodo-is-api
Version: 0.8.0
Summary: 
Author: Eldos
Author-email: eldos.baktybekov@gmail.com
Requires-Python: >=3.11,<4.0
Classifier: Programming Language :: Python :: 3
Classifier: Programming Language :: Python :: 3.11
Requires-Dist: httpx (>=0.23.3,<0.24.0)
Requires-Dist: pydantic (>=1.10.9,<2.0.0)
Requires-Dist: structlog (>=23.1.0,<24.0.0)
